yaconfig/__init__.py
yaconfig-0.6.1.dist-info/licenses/LICENSE.txt
yaconfig-0.6.1.dist-info/METADATA
yaconfig-0.6.1.dist-info/WHEEL
yaconfig-0.6.1.dist-info/top_level.txt
yaconfig-0.6.1.dist-info/RECORD
